LICENSE
README.md
setup.py
fcm_mp/FCM_MP.py
fcm_mp/__init__.py
fcm_mp.egg-info/PKG-INFO
fcm_mp.egg-info/SOURCES.txt
fcm_mp.egg-info/dependency_links.txt
fcm_mp.egg-info/requires.txt
fcm_mp.egg-info/top_level.txt