Metadata-Version: 2.1
Name: fcm-mp
Version: 0.1.0
Summary: Fuzzy Cognitive Map with Moore-Penrose inverse learning
Home-page: https://github.com/gnapoles/fcm_mp
Author: Gonzalo Nápoles
Author-email: g.r.napoles@uvt.nl
License: Apache License 2.0
Classifier: Development Status :: 1 - Planning
Classifier: Intended Audience :: Science/Research
Classifier: License :: OSI Approved :: Apache Software License
Classifier: Operating System :: Microsoft :: Windows
Classifier: Operating System :: MacOS
Classifier: Programming Language :: Python :: 3.8
License-File: LICENSE
